CardiacModelGenerator/.gitignore
CardiacModelGenerator/CardiacModelGenerator.py
CardiacModelGenerator/_init_.py
CardiacModelGenerator/static/mesh_intro_pic.png
cardiacmodelgenerator-0.1.9.dist-info/METADATA
cardiacmodelgenerator-0.1.9.dist-info/WHEEL
cardiacmodelgenerator-0.1.9.dist-info/entry_points.txt
cardiacmodelgenerator-0.1.9.dist-info/licenses/LICENSE
cardiacmodelgenerator-0.1.9.dist-info/RECORD
