Metadata-Version: 2.3
Name: CardiacModelGenerator
Version: 0.1.9
Summary: Generate 3D model from clinical cardiac imaging data 
Project-URL: Homepage, https://github.com/vjaniuw/CardiacModelGenerator
Project-URL: Documentation, https://github.com/vjaniuw/CardiacModelGenerator/wiki
Project-URL: Repository, https://github.com/vjaniuw/CardiacModelGenerator
Project-URL: Bug Tracker, https://github.com/vjaniuw/CardiacModelGenerator/issues
Author-email: Vinay Jani <vjani@uw.edu>
License: MIT License
Keywords: 3D,VTK,cardiac,medical imaging,modeling
Classifier: Development Status :: 4 - Beta
Classifier: Intended Audience :: Science/Research
Classifier: License :: OSI Approved :: MIT License
Classifier: Programming Language :: Python :: 3.8
Classifier: Programming Language :: Python :: 3.9
Classifier: Topic :: Scientific/Engineering :: Medical Science Apps.
Requires-Python: >=3.9
Requires-Dist: matplotlib<4.0.0,>=3.4.0
Requires-Dist: nibabel<6.0.0,>=3.0.0
Requires-Dist: numpy<2.0.0,>=1.21.0
Requires-Dist: opencv-python<5.0.0,>=4.5.0
Requires-Dist: pydicom<3.0.0,>=2.2.0
Requires-Dist: pyvista<0.50.0,>=0.32.0
Requires-Dist: wxpython>=4.2.2
Provides-Extra: dev
Requires-Dist: black; extra == 'dev'
Requires-Dist: flake8; extra == 'dev'
